{
  "id": "122",
  "rows": [
    {
      "answer": "lay",
      "clue": "\"___ it on me!\" (3)"
    },
    {
      "answer": "ally",
      "clue": "Coalition member (4)"
    },
    {
      "answer": "sally",
      "clue": "Astronaut Ride (5)"
    },
    {
      "answer": "ballsy",
      "clue": "Audacious (6)"
    },
    {
      "answer": "allboys",
      "clue": "Like certain prep schools (3,4)"
    },
    {
      "answer": "lazyslob",
      "clue": "One who makes a terrible house guest (4,4)"
    }
  ]
}
