{
  "id": "278",
  "rows": [
    {
      "answer": "sop",
      "clue": "Soak up (3)"
    },
    {
      "answer": "post",
      "clue": "Mail (4)"
    },
    {
      "answer": "ports",
      "clue": "Wine varieties (5)"
    },
    {
      "answer": "pastor",
      "clue": "Shepherd of a sort (6)"
    },
    {
      "answer": "raptors",
      "clue": "Hawks, e.g. (7)"
    },
    {
      "answer": "prorates",
      "clue": "Divides proportionally (8)"
    },
    {
      "answer": "starpower",
      "clue": "Celebrity pull (4,5)"
    },
    {
      "answer": "topdrawers",
      "clue": "Sock holders, maybe (3,7)"
    },
    {
      "answer": "stepforward",
      "clue": "Volunteer (4,7)"
    },
    {
      "answer": "dropsofwater",
      "clue": "Rain, essentially (5,2,5)"
    }
  ]
}
